{
  "_metadata": {
    "version": "2603.04.001"
  },
  "৭০৪": {
    "name": "মহানগর প্রভাতী",
    "runsOn": [
      "শুক্র",
      "শনি",
      "রবি",
      "সোম",
      "মঙ্গল",
      "বুধ",
      "বৃহস্পতি"
    ],
    "routes": [
      {
        "station": "ঢাকা",
        "arrival": "",
        "departure": "07:45",
        "halt": "",
        "duration": ""
      },
      {
        "station": "বিমানবন্দর",
        "arrival": "08:07",
        "departure": "08:12",
        "halt": "00:05",
        "duration": "00:22"
      },
      {
        "station": "নরসিংদী",
        "arrival": "08:51",
        "departure": "08:53",
        "halt": "00:02",
        "duration": "00:39"
      },
      {
        "station": "ভৈরব",
        "arrival": "09:19",
        "departure": "09:22",
        "halt": "00:03",
        "duration": "00:26"
      },
      {
        "station": "বি বাড়িয়া",
        "arrival": "09:40",
        "departure": "09:44",
        "halt": "00:04",
        "duration": "00:18"
      },
      {
        "station": "আখাউড়া",
        "arrival": "10:05",
        "departure": "10:08",
        "halt": "00:03",
        "duration": "00:21"
      },
      {
        "station": "কুমিল্লা",
        "arrival": "10:51",
        "departure": "10:53",
        "halt": "00:02",
        "duration": "00:43"
      },
      {
        "station": "লাকসাম",
        "arrival": "11:15",
        "departure": "11:17",
        "halt": "00:02",
        "duration": "00:22"
      },
      {
        "station": "গুণবতী",
        "arrival": "11:43",
        "departure": "11:45",
        "halt": "00:02",
        "duration": "00:26"
      },
      {
        "station": "ফেনী",
        "arrival": "12:00",
        "departure": "12:02",
        "halt": "00:02",
        "duration": "00:15"
      },
      {
        "station": "চট্টগ্রাম",
        "arrival": "13:35",
        "departure": "",
        "halt": "",
        "duration": "01:33"
      }
    ],
    "totalDuration": "05:50"
  },
  "৭০৩": {
    "name": "মহানগর গোধূলি",
    "runsOn": [
      "শুক্র",
      "শনি",
      "রবি",
      "সোম",
      "মঙ্গল",
      "বুধ",
      "বৃহস্পতি"
    ],
    "routes": [
      {
        "station": "চট্টগ্রাম",
        "arrival": "",
        "departure": "15:00",
        "halt": "",
        "duration": ""
      },
      {
        "station": "ফেনী",
        "arrival": "16:20",
        "departure": "16:22",
        "halt": "00:02",
        "duration": "01:20"
      },
      {
        "station": "গুণবতী",
        "arrival": "16:36",
        "departure": "16:38",
        "halt": "00:02",
        "duration": "00:14"
      },
      {
        "station": "লাকসাম",
        "arrival": "17:04",
        "departure": "17:06",
        "halt": "00:02",
        "duration": "00:26"
      },
      {
        "station": "কুমিল্লা",
        "arrival": "17:27",
        "departure": "17:29",
        "halt": "00:02",
        "duration": "00:21"
      },
      {
        "station": "আখাউড়া",
        "arrival": "18:20",
        "departure": "18:23",
        "halt": "00:03",
        "duration": "00:51"
      },
      {
        "station": "বি বাড়িয়া",
        "arrival": "18:41",
        "departure": "18:45",
        "halt": "00:04",
        "duration": "00:18"
      },
      {
        "station": "ভৈরব",
        "arrival": "19:05",
        "departure": "19:08",
        "halt": "00:03",
        "duration": "00:20"
      },
      {
        "station": "নরসিংদী",
        "arrival": "19:36",
        "departure": "19:38",
        "halt": "00:02",
        "duration": "00:28"
      },
      {
        "station": "বিমানবন্দর",
        "arrival": "20:15",
        "departure": "20:18",
        "halt": "00:03",
        "duration": "00:39"
      },
      {
        "station": "ঢাকা",
        "arrival": "20:45",
        "departure": "",
        "halt": "",
        "duration": "00:27"
      }
    ],
    "totalDuration": "05:45"
  },
  "৭৮১": {
    "name": "কিশোরগঞ্জ এক্সপ্রেস",
    "runsOn": [
      "শুক্র",
      "শনি",
      "রবি",
      "সোম",
      "বুধ",
      "বৃহস্পতি"
    ],
    "routes": [
      {
        "station": "ঢাকা",
        "arrival": "",
        "departure": "10:30",
        "halt": "",
        "duration": ""
      },
      {
        "station": "বিমানবন্দর",
        "arrival": "10:52",
        "departure": "10:57",
        "halt": "00:05",
        "duration": "00:22"
      },
      {
        "station": "নরসিংদী",
        "arrival": "11:36",
        "departure": "11:39",
        "halt": "00:03",
        "duration": "00:39"
      },
      {
        "station": "মেথিকান্দা",
        "arrival": "11:57",
        "departure": "11:59",
        "halt": "00:02",
        "duration": "00:18"
      },
      {
        "station": "ভৈরব",
        "arrival": "12:15",
        "departure": "12:35",
        "halt": "00:20",
        "duration": "00:16"
      },
      {
        "station": "কুলিয়ারচর",
        "arrival": "12:54",
        "departure": "12:56",
        "halt": "00:02",
        "duration": "00:19"
      },
      {
        "station": "বাজিতপুর",
        "arrival": "13:04",
        "departure": "13:06",
        "halt": "00:02",
        "duration": "00:08"
      },
      {
        "station": "সরারচর",
        "arrival": "13:14",
        "departure": "13:16",
        "halt": "00:02",
        "duration": "00:08"
      },
      {
        "station": "মানিকখালী",
        "arrival": "13:31",
        "departure": "13:33",
        "halt": "00:02",
        "duration": "00:15"
      },
      {
        "station": "গচিহাটা",
        "arrival": "13:40",
        "departure": "13:42",
        "halt": "00:02",
        "duration": "00:07"
      },
      {
        "station": "কিশোরগঞ্জ",
        "arrival": "14:10",
        "departure": "",
        "halt": "",
        "duration": "00:28"
      }
    ],
    "totalDuration": "03:40"
  },
  "৭৮২": {
    "name": "কিশোরগঞ্জ এক্সপ্রেস",
    "runsOn": [
      "শুক্র",
      "শনি",
      "রবি",
      "সোম",
      "বুধ",
      "বৃহস্পতি"
    ],
    "routes": [
      {
        "station": "কিশোরগঞ্জ",
        "arrival": "",
        "departure": "16:00",
        "halt": "",
        "duration": ""
      },
      {
        "station": "গচিহাটা",
        "arrival": "16:15",
        "departure": "16:17",
        "halt": "00:02",
        "duration": "00:15"
      },
      {
        "station": "মানিকখালী",
        "arrival": "16:27",
        "departure": "16:29",
        "halt": "00:02",
        "duration": "00:10"
      },
      {
        "station": "সরারচর",
        "arrival": "16:45",
        "departure": "16:47",
        "halt": "00:02",
        "duration": "00:16"
      },
      {
        "station": "বাজিতপুর",
        "arrival": "16:55",
        "departure": "16:57",
        "halt": "00:02",
        "duration": "00:08"
      },
      {
        "station": "কুলিয়ারচর",
        "arrival": "17:05",
        "departure": "17:07",
        "halt": "00:02",
        "duration": "00:08"
      },
      {
        "station": "ভৈরব",
        "arrival": "17:28",
        "departure": "17:48",
        "halt": "00:20",
        "duration": "00:21"
      },
      {
        "station": "মেথিকান্দা",
        "arrival": "18:04",
        "departure": "18:06",
        "halt": "00:02",
        "duration": "00:16"
      },
      {
        "station": "নরসিংদী",
        "arrival": "18:27",
        "departure": "18:30",
        "halt": "00:03",
        "duration": "00:21"
      },
      {
        "station": "বিমানবন্দর",
        "arrival": "19:20",
        "departure": "",
        "halt": "",
        "duration": "00:50"
      },
      {
        "station": "ঢাকা",
        "arrival": "20:00",
        "departure": "",
        "halt": "",
        "duration": ""
      }
    ],
    "totalDuration": "04:00"
  },
  "৮০১": {
    "name": "চট্টলা এক্সপ্রেস",
    "runsOn": [
      "শনি",
      "রবি",
      "সোম",
      "মঙ্গল",
      "বুধ",
      "বৃহস্পতি"
    ],
    "routes": [
      {
        "station": "চট্টগ্রাম",
        "arrival": "",
        "departure": "06:00",
        "halt": "",
        "duration": ""
      },
      {
        "station": "কুমিরা",
        "arrival": "06:26",
        "departure": "06:28",
        "halt": "00:02",
        "duration": "00:26"
      },
      {
        "station": "ফেনী",
        "arrival": "07:28",
        "departure": "07:31",
        "halt": "00:03",
        "duration": "01:00"
      },
      {
        "station": "হাসানপুর",
        "arrival": "07:52",
        "departure": "07:54",
        "halt": "00:02",
        "duration": "00:21"
      },
      {
        "station": "নাঙ্গলকোট",
        "arrival": "08:02",
        "departure": "08:04",
        "halt": "00:02",
        "duration": "00:08"
      },
      {
        "station": "লাকসাম",
        "arrival": "08:17",
        "departure": "08:20",
        "halt": "00:03",
        "duration": "00:13"
      },
      {
        "station": "কুমিল্লা",
        "arrival": "08:41",
        "departure": "08:44",
        "halt": "00:03",
        "duration": "00:21"
      },
      {
        "station": "শশীদল",
        "arrival": "09:05",
        "departure": "09:07",
        "halt": "00:02",
        "duration": "00:21"
      },
      {
        "station": "কসবা",
        "arrival": "09:39",
        "departure": "09:41",
        "halt": "00:02",
        "duration": "00:32"
      },
      {
        "station": "আখাউড়া",
        "arrival": "10:05",
        "departure": "10:08",
        "halt": "00:03",
        "duration": "00:24"
      },
      {
        "station": "বি বাড়িয়া",
        "arrival": "10:26",
        "departure": "10:29",
        "halt": "00:03",
        "duration": "00:18"
      },
      {
        "station": "ভৈরব",
        "arrival": "10:50",
        "departure": "10:53",
        "halt": "00:03",
        "duration": "00:21"
      },
      {
        "station": "মেথিকান্দা",
        "arrival": "11:08",
        "departure": "11:10",
        "halt": "00:02",
        "duration": "00:15"
      },
      {
        "station": "নরসিংদী",
        "arrival": "11:27",
        "departure": "11:30",
        "halt": "00:03",
        "duration": "00:17"
      },
      {
        "station": "বিমানবন্দর",
        "arrival": "12:10",
        "departure": "12:13",
        "halt": "00:03",
        "duration": "00:40"
      },
      {
        "station": "ঢাকা",
        "arrival": "12:40",
        "departure": "",
        "halt": "",
        "duration": "00:27"
      }
    ],
    "totalDuration": "06:40"
  },
  "৮০২": {
    "name": "চট্টলা এক্সপ্রেস",
    "runsOn": [
      "শনি",
      "রবি",
      "সোম",
      "মঙ্গল",
      "বুধ",
      "বৃহস্পতি"
    ],
    "routes": [
      {
        "station": "ঢাকা",
        "arrival": "",
        "departure": "14:15",
        "halt": "",
        "duration": ""
      },
      {
        "station": "বিমানবন্দর",
        "arrival": "14:38",
        "departure": "14:43",
        "halt": "00:05",
        "duration": "00:23"
      },
      {
        "station": "নরসিংদী",
        "arrival": "15:20",
        "departure": "15:23",
        "halt": "00:03",
        "duration": "00:37"
      },
      {
        "station": "মেথিকান্দা",
        "arrival": "15:41",
        "departure": "15:43",
        "halt": "00:02",
        "duration": "00:18"
      },
      {
        "station": "ভৈরব",
        "arrival": "15:57",
        "departure": "16:00",
        "halt": "00:03",
        "duration": "00:14"
      },
      {
        "station": "বি বাড়িয়া",
        "arrival": "16:19",
        "departure": "16:23",
        "halt": "00:04",
        "duration": "00:19"
      },
      {
        "station": "আখাউড়া",
        "arrival": "16:42",
        "departure": "16:45",
        "halt": "00:03",
        "duration": "00:19"
      },
      {
        "station": "কসবা",
        "arrival": "17:01",
        "departure": "17:03",
        "halt": "00:02",
        "duration": "00:16"
      },
      {
        "station": "শশীদল",
        "arrival": "17:16",
        "departure": "17:18",
        "halt": "00:02",
        "duration": "00:13"
      },
      {
        "station": "কুমিল্লা",
        "arrival": "17:40",
        "departure": "17:42",
        "halt": "00:02",
        "duration": "00:22"
      },
      {
        "station": "লাকসাম",
        "arrival": "18:04",
        "departure": "18:07",
        "halt": "00:03",
        "duration": "00:22"
      },
      {
        "station": "নাঙ্গলকোট",
        "arrival": "18:21",
        "departure": "18:23",
        "halt": "00:02",
        "duration": "00:14"
      },
      {
        "station": "হাসানপুর",
        "arrival": "18:30",
        "departure": "18:32",
        "halt": "00:02",
        "duration": "00:07"
      },
      {
        "station": "ফেনী",
        "arrival": "18:53",
        "departure": "18:55",
        "halt": "00:02",
        "duration": "00:21"
      },
      {
        "station": "কুমিরা",
        "arrival": "19:56",
        "departure": "19:58",
        "halt": "00:02",
        "duration": "01:01"
      },
      {
        "station": "চট্টগ্রাম",
        "arrival": "20:30",
        "departure": "",
        "halt": "",
        "duration": "00:32"
      }
    ],
    "totalDuration": "06:15"
  },
  "৭১১": {
    "name": "উপকূল এক্সপ্রেস",
    "runsOn": [
      "শুক্র",
      "শনি",
      "রবি",
      "সোম",
      "মঙ্গল",
      "বুধ"
    ],
    "routes": [
      {
        "station": "নোয়াখালী",
        "arrival": "",
        "departure": "06:00",
        "halt": "",
        "duration": ""
      },
      {
        "station": "মাইজদী কোর্ট",
        "arrival": "06:07",
        "departure": "06:09",
        "halt": "00:02",
        "duration": "00:07"
      },
      {
        "station": "চৌমুহনী",
        "arrival": "06:23",
        "departure": "06:25",
        "halt": "00:02",
        "duration": "00:14"
      },
      {
        "station": "বজরা",
        "arrival": "06:34",
        "departure": "06:36",
        "halt": "00:02",
        "duration": "00:09"
      },
      {
        "station": "সোনাইমুড়ি",
        "arrival": "06:45",
        "departure": "06:47",
        "halt": "00:02",
        "duration": "00:09"
      },
      {
        "station": "নাথেরপেটুয়া",
        "arrival": "07:00",
        "departure": "07:02",
        "halt": "00:02",
        "duration": "00:13"
      },
      {
        "station": "লাকসাম",
        "arrival": "07:25",
        "departure": "07:30",
        "halt": "00:05",
        "duration": "00:23"
      },
      {
        "station": "কুমিল্লা",
        "arrival": "07:52",
        "departure": "07:54",
        "halt": "00:02",
        "duration": "00:22"
      },
      {
        "station": "কসবা",
        "arrival": "08:24",
        "departure": "08:26",
        "halt": "00:02",
        "duration": "00:30"
      },
      {
        "station": "আখাউড়া",
        "arrival": "08:50",
        "departure": "08:53",
        "halt": "00:03",
        "duration": "00:24"
      },
      {
        "station": "বি বাড়িয়া",
        "arrival": "09:11",
        "departure": "09:15",
        "halt": "00:04",
        "duration": "00:18"
      },
      {
        "station": "আশুগঞ্জ",
        "arrival": "09:30",
        "departure": "09:32",
        "halt": "00:02",
        "duration": "00:15"
      },
      {
        "station": "নরসিংদী",
        "arrival": "10:05",
        "departure": "10:07",
        "halt": "00:02",
        "duration": "00:33"
      },
      {
        "station": "বিমানবন্দর",
        "arrival": "10:47",
        "departure": "10:50",
        "halt": "00:03",
        "duration": "00:40"
      },
      {
        "station": "ঢাকা",
        "arrival": "11:20",
        "departure": "",
        "halt": "",
        "duration": ""
      }
    ],
    "totalDuration": "05:20"
  },
  "৭১২": {
    "name": "উপকূল এক্সপ্রেস",
    "runsOn": [
      "শুক্র",
      "শনি",
      "রবি",
      "সোম",
      "মঙ্গল",
      "বৃহস্পতি"
    ],
    "routes": [
      {
        "station": "ঢাকা",
        "arrival": "",
        "departure": "15:10",
        "halt": "",
        "duration": ""
      },
      {
        "station": "বিমানবন্দর",
        "arrival": "15:33",
        "departure": "15:38",
        "halt": "00:05",
        "duration": "00:23"
      },
      {
        "station": "নরসিংদী",
        "arrival": "16:17",
        "departure": "16:20",
        "halt": "00:03",
        "duration": "00:39"
      },
      {
        "station": "ভৈরব",
        "arrival": "16:50",
        "departure": "16:53",
        "halt": "00:03",
        "duration": "00:30"
      },
      {
        "station": "আশুগঞ্জ",
        "arrival": "17:00",
        "departure": "17:03",
        "halt": "00:03",
        "duration": "00:07"
      },
      {
        "station": "বি বাড়িয়া",
        "arrival": "17:17",
        "departure": "17:21",
        "halt": "00:04",
        "duration": "00:14"
      },
      {
        "station": "আখাউড়া",
        "arrival": "17:47",
        "departure": "17:50",
        "halt": "00:03",
        "duration": "00:26"
      },
      {
        "station": "কসবা",
        "arrival": "18:06",
        "departure": "18:08",
        "halt": "00:02",
        "duration": "00:16"
      },
      {
        "station": "কুমিল্লা",
        "arrival": "18:38",
        "departure": "18:40",
        "halt": "00:02",
        "duration": "00:30"
      },
      {
        "station": "লাকসাম",
        "arrival": "19:03",
        "departure": "19:06",
        "halt": "00:03",
        "duration": "00:23"
      },
      {
        "station": "নাথেরপেটুয়া",
        "arrival": "19:28",
        "departure": "",
        "halt": "",
        "duration": "00:22"
      },
      {
        "station": "সোনাইমুড়ি",
        "arrival": "19:42",
        "departure": "",
        "halt": "",
        "duration": ""
      },
      {
        "station": "বজরা",
        "arrival": "19:53",
        "departure": "",
        "halt": "",
        "duration": ""
      },
      {
        "station": "চৌমুহনী",
        "arrival": "20:04",
        "departure": "20:06",
        "halt": "00:02",
        "duration": ""
      },
      {
        "station": "মাইজদী কোর্ট",
        "arrival": "20:20",
        "departure": "",
        "halt": "",
        "duration": "00:14"
      },
      {
        "station": "নোয়াখালী",
        "arrival": "20:40",
        "departure": "",
        "halt": "",
        "duration": ""
      }
    ],
    "totalDuration": "05:30"
  },
  "৭৩৭": {
    "name": "এগারোসিন্ধুর প্রভাতী",
    "runsOn": [
      "শুক্র",
      "শনি",
      "রবি",
      "সোম",
      "মঙ্গল",
      "বৃহস্পতি"
    ],
    "routes": [
      {
        "station": "ঢাকা",
        "arrival": "",
        "departure": "07:15",
        "halt": "",
        "duration": ""
      },
      {
        "station": "বিমানবন্দর",
        "arrival": "07:38",
        "departure": "07:43",
        "halt": "00:05",
        "duration": "00:23"
      },
      {
        "station": "নরসিংদী",
        "arrival": "08:22",
        "departure": "08:24",
        "halt": "00:02",
        "duration": "00:39"
      },
      {
        "station": "মেথিকান্দা",
        "arrival": "08:38",
        "departure": "08:40",
        "halt": "00:02",
        "duration": "00:14"
      },
      {
        "station": "ভৈরব",
        "arrival": "08:53",
        "departure": "09:13",
        "halt": "00:20",
        "duration": "00:13"
      },
      {
        "station": "কুলিয়ারচর",
        "arrival": "09:32",
        "departure": "09:34",
        "halt": "00:02",
        "duration": "00:19"
      },
      {
        "station": "বাজিতপুর",
        "arrival": "09:42",
        "departure": "09:44",
        "halt": "00:02",
        "duration": "00:08"
      },
      {
        "station": "সরারচর",
        "arrival": "09:52",
        "departure": "09:54",
        "halt": "00:02",
        "duration": "00:08"
      },
      {
        "station": "মানিকখালী",
        "arrival": "10:10",
        "departure": "10:12",
        "halt": "00:02",
        "duration": "00:16"
      },
      {
        "station": "গচিহাটা",
        "arrival": "10:22",
        "departure": "10:24",
        "halt": "00:02",
        "duration": "00:10"
      },
      {
        "station": "কিশোরগঞ্জ",
        "arrival": "11:10",
        "departure": "",
        "halt": "",
        "duration": "00:46"
      }
    ],
    "totalDuration": "03:55"
  },
  "৭৩৮": {
    "name": "এগারোসিন্ধুর প্রভাতী",
    "runsOn": [
      "শুক্র",
      "শনি",
      "রবি",
      "সোম",
      "মঙ্গল",
      "বুধ",
      "বৃহস্পতি"
    ],
    "routes": [
      {
        "station": "কিশোরগঞ্জ",
        "arrival": "",
        "departure": "06:30",
        "halt": "",
        "duration": ""
      },
      {
        "station": "গচিহাটা",
        "arrival": "06:45",
        "departure": "06:47",
        "halt": "00:02",
        "duration": "00:15"
      },
      {
        "station": "মানিকখালী",
        "arrival": "06:57",
        "departure": "06:59",
        "halt": "00:02",
        "duration": "00:10"
      },
      {
        "station": "সরারচর",
        "arrival": "07:15",
        "departure": "07:17",
        "halt": "00:02",
        "duration": "00:16"
      },
      {
        "station": "বাজিতপুর",
        "arrival": "07:25",
        "departure": "07:27",
        "halt": "00:02",
        "duration": "00:08"
      },
      {
        "station": "কুলিয়ারচর",
        "arrival": "07:35",
        "departure": "07:37",
        "halt": "00:02",
        "duration": "00:08"
      },
      {
        "station": "ভৈরব",
        "arrival": "08:00",
        "departure": "08:20",
        "halt": "00:20",
        "duration": "00:23"
      },
      {
        "station": "মেথিকান্দা",
        "arrival": "08:38",
        "departure": "08:40",
        "halt": "00:02",
        "duration": "00:18"
      },
      {
        "station": "নরসিংদী",
        "arrival": "09:02",
        "departure": "09:04",
        "halt": "00:02",
        "duration": "00:22"
      },
      {
        "station": "বিমানবন্দর",
        "arrival": "09:53",
        "departure": "",
        "halt": "",
        "duration": "00:49"
      },
      {
        "station": "ঢাকা",
        "arrival": "10:35",
        "departure": "",
        "halt": "",
        "duration": ""
      }
    ],
    "totalDuration": "04:05"
  },
  "৭৪৯": {
    "name": "এগারোসিন্ধুর গোধূলি",
    "runsOn": [
      "শুক্র",
      "শনি",
      "রবি",
      "সোম",
      "মঙ্গল",
      "বুধ",
      "বৃহস্পতি"
    ],
    "routes": [
      {
        "station": "ঢাকা",
        "arrival": "",
        "departure": "18:45",
        "halt": "",
        "duration": ""
      },
      {
        "station": "বিমানবন্দর",
        "arrival": "19:08",
        "departure": "19:13",
        "halt": "00:05",
        "duration": "00:23"
      },
      {
        "station": "নরসিংদী",
        "arrival": "19:53",
        "departure": "19:55",
        "halt": "00:02",
        "duration": "00:40"
      },
      {
        "station": "মেথিকান্দা",
        "arrival": "20:12",
        "departure": "20:14",
        "halt": "00:02",
        "duration": "00:17"
      },
      {
        "station": "ভৈরব",
        "arrival": "20:30",
        "departure": "20:50",
        "halt": "00:20",
        "duration": "00:16"
      },
      {
        "station": "কুলিয়ারচর",
        "arrival": "21:09",
        "departure": "21:11",
        "halt": "00:02",
        "duration": "00:19"
      },
      {
        "station": "বাজিতপুর",
        "arrival": "21:20",
        "departure": "21:22",
        "halt": "00:02",
        "duration": "00:09"
      },
      {
        "station": "সরারচর",
        "arrival": "21:30",
        "departure": "21:32",
        "halt": "00:02",
        "duration": "00:08"
      },
      {
        "station": "মানিকখালী",
        "arrival": "21:48",
        "departure": "21:50",
        "halt": "00:02",
        "duration": "00:16"
      },
      {
        "station": "গচিহাটা",
        "arrival": "22:00",
        "departure": "22:02",
        "halt": "00:02",
        "duration": "00:10"
      },
      {
        "station": "কিশোরগঞ্জ",
        "arrival": "22:40",
        "departure": "",
        "halt": "",
        "duration": "00:38"
      }
    ],
    "totalDuration": "03:55"
  },
  "৭৫০": {
    "name": "এগারোসিন্ধুর গোধূলি",
    "runsOn": [
      "শুক্র",
      "শনি",
      "রবি",
      "সোম",
      "মঙ্গল",
      "বৃহস্পতি"
    ],
    "routes": [
      {
        "station": "কিশোরগঞ্জ",
        "arrival": "",
        "departure": "12:50",
        "halt": "",
        "duration": ""
      },
      {
        "station": "গচিহাটা",
        "arrival": "13:06",
        "departure": "13:08",
        "halt": "00:02",
        "duration": "00:16"
      },
      {
        "station": "মানিকখালী",
        "arrival": "13:31",
        "departure": "13:33",
        "halt": "00:02",
        "duration": "00:23"
      },
      {
        "station": "সরারচর",
        "arrival": "13:52",
        "departure": "13:54",
        "halt": "00:02",
        "duration": "00:19"
      },
      {
        "station": "বাজিতপুর",
        "arrival": "14:03",
        "departure": "14:05",
        "halt": "00:02",
        "duration": "00:09"
      },
      {
        "station": "কুলিয়ারচর",
        "arrival": "14:13",
        "departure": "14:15",
        "halt": "00:02",
        "duration": "00:08"
      },
      {
        "station": "ভৈরব",
        "arrival": "14:40",
        "departure": "15:00",
        "halt": "00:20",
        "duration": "00:25"
      },
      {
        "station": "মেথিকান্দা",
        "arrival": "15:13",
        "departure": "15:15",
        "halt": "00:02",
        "duration": "00:13"
      },
      {
        "station": "নরসিংদী",
        "arrival": "15:29",
        "departure": "15:31",
        "halt": "00:02",
        "duration": "00:14"
      },
      {
        "station": "বিমানবন্দর",
        "arrival": "16:12",
        "departure": "",
        "halt": "",
        "duration": "00:41"
      },
      {
        "station": "ঢাকা",
        "arrival": "16:45",
        "departure": "",
        "halt": "",
        "duration": ""
      }
    ],
    "totalDuration": "03:55"
  },
  "৭২১": {
    "name": "মহানগর এক্সপ্রেস",
    "runsOn": [
      "শুক্র",
      "শনি",
      "সোম",
      "মঙ্গল",
      "বুধ",
      "বৃহস্পতি"
    ],
    "routes": [
      {
        "station": "চট্টগ্রাম",
        "arrival": "",
        "departure": "12:30",
        "halt": "",
        "duration": ""
      },
      {
        "station": "কুমিরা",
        "arrival": "12:56",
        "departure": "12:58",
        "halt": "00:02",
        "duration": "00:26"
      },
      {
        "station": "ফেনী",
        "arrival": "13:57",
        "departure": "13:59",
        "halt": "00:02",
        "duration": "00:59"
      },
      {
        "station": "নাঙ্গলকোট",
        "arrival": "14:24",
        "departure": "14:26",
        "halt": "00:02",
        "duration": "00:25"
      },
      {
        "station": "লাকসাম",
        "arrival": "14:42",
        "departure": "14:44",
        "halt": "00:02",
        "duration": "00:16"
      },
      {
        "station": "কুমিল্লা",
        "arrival": "15:06",
        "departure": "15:08",
        "halt": "00:02",
        "duration": "00:22"
      },
      {
        "station": "কসবা",
        "arrival": "15:38",
        "departure": "15:40",
        "halt": "00:02",
        "duration": "00:30"
      },
      {
        "station": "আখাউড়া",
        "arrival": "16:05",
        "departure": "16:08",
        "halt": "00:03",
        "duration": "00:25"
      },
      {
        "station": "বি বাড়িয়া",
        "arrival": "16:26",
        "departure": "16:30",
        "halt": "00:04",
        "duration": "00:18"
      },
      {
        "station": "আশুগঞ্জ",
        "arrival": "16:45",
        "departure": "16:47",
        "halt": "00:02",
        "duration": "00:15"
      },
      {
        "station": "ভৈরব",
        "arrival": "16:55",
        "departure": "16:57",
        "halt": "00:02",
        "duration": "00:08"
      },
      {
        "station": "নরসিংদী",
        "arrival": "17:27",
        "departure": "17:29",
        "halt": "00:02",
        "duration": "00:30"
      },
      {
        "station": "বিমানবন্দর",
        "arrival": "18:07",
        "departure": "18:10",
        "halt": "00:03",
        "duration": "00:40"
      },
      {
        "station": "ঢাকা",
        "arrival": "18:40",
        "departure": "",
        "halt": "",
        "duration": "00:30"
      }
    ],
    "totalDuration": "06:10"
  },
  "৭২২": {
    "name": "মহানগর এক্সপ্রেস",
    "runsOn": [
      "শুক্র",
      "শনি",
      "সোম",
      "মঙ্গল",
      "বুধ",
      "বৃহস্পতি"
    ],
    "routes": [
      {
        "station": "ঢাকা",
        "arrival": "",
        "departure": "21:20",
        "halt": "",
        "duration": ""
      },
      {
        "station": "বিমানবন্দর",
        "arrival": "21:43",
        "departure": "21:48",
        "halt": "00:05",
        "duration": "00:23"
      },
      {
        "station": "নরসিংদী",
        "arrival": "22:27",
        "departure": "22:30",
        "halt": "00:03",
        "duration": "00:39"
      },
      {
        "station": "ভৈরব",
        "arrival": "23:00",
        "departure": "23:03",
        "halt": "00:03",
        "duration": "00:30"
      },
      {
        "station": "আশুগঞ্জ",
        "arrival": "23:11",
        "departure": "23:13",
        "halt": "00:02",
        "duration": "00:08"
      },
      {
        "station": "বি বাড়িয়া",
        "arrival": "23:28",
        "departure": "23:31",
        "halt": "00:03",
        "duration": "00:15"
      },
      {
        "station": "আখাউড়া",
        "arrival": "23:55",
        "departure": "23:58",
        "halt": "00:03",
        "duration": "00:24"
      },
      {
        "station": "কসবা",
        "arrival": "00:14",
        "departure": "00:16",
        "halt": "00:02",
        "duration": "00:16"
      },
      {
        "station": "কুমিল্লা",
        "arrival": "00:46",
        "departure": "00:48",
        "halt": "00:02",
        "duration": "00:30"
      },
      {
        "station": "লাকসাম",
        "arrival": "01:10",
        "departure": "01:12",
        "halt": "00:02",
        "duration": "00:22"
      },
      {
        "station": "নাঙ্গলকোট",
        "arrival": "01:26",
        "departure": "01:28",
        "halt": "00:02",
        "duration": "00:14"
      },
      {
        "station": "ফেনী",
        "arrival": "01:53",
        "departure": "01:55",
        "halt": "00:02",
        "duration": "00:25"
      },
      {
        "station": "কুমিরা",
        "arrival": "02:55",
        "departure": "",
        "halt": "",
        "duration": "01:00"
      },
      {
        "station": "চট্টগ্রাম",
        "arrival": "03:30",
        "departure": "",
        "halt": "",
        "duration": ""
      }
    ],
    "totalDuration": "06:10"
  },
  "৭৩৯": {
    "name": "উপবন এক্সপ্রেস",
    "runsOn": [
      "শুক্র",
      "শনি",
      "রবি",
      "সোম",
      "মঙ্গল",
      "বৃহস্পতি"
    ],
    "routes": [
      {
        "station": "ঢাকা",
        "arrival": "",
        "departure": "22:00",
        "halt": "",
        "duration": ""
      },
      {
        "station": "বিমানবন্দর",
        "arrival": "22:23",
        "departure": "22:28",
        "halt": "00:05",
        "duration": "00:23"
      },
      {
        "station": "নরসিংদী",
        "arrival": "23:09",
        "departure": "23:11",
        "halt": "00:02",
        "duration": "00:41"
      },
      {
        "station": "ভৈরব",
        "arrival": "23:40",
        "departure": "23:43",
        "halt": "00:03",
        "duration": "00:29"
      },
      {
        "station": "শায়েস্তাগঞ্জ",
        "arrival": "01:22",
        "departure": "01:25",
        "halt": "00:03",
        "duration": "01:39"
      },
      {
        "station": "শ্রীমঙ্গল",
        "arrival": "02:09",
        "departure": "02:11",
        "halt": "00:02",
        "duration": "00:44"
      },
      {
        "station": "ভানুগাছ",
        "arrival": "02:30",
        "departure": "02:32",
        "halt": "00:02",
        "duration": "00:19"
      },
      {
        "station": "শমসেরনগর",
        "arrival": "02:41",
        "departure": "02:43",
        "halt": "00:02",
        "duration": "00:09"
      },
      {
        "station": "কুলাউড়া",
        "arrival": "03:08",
        "departure": "03:11",
        "halt": "00:03",
        "duration": "00:25"
      },
      {
        "station": "বরমচাল",
        "arrival": "03:25",
        "departure": "03:27",
        "halt": "00:02",
        "duration": "00:14"
      },
      {
        "station": "মাইজগাঁও",
        "arrival": "03:43",
        "departure": "03:45",
        "halt": "00:02",
        "duration": "00:16"
      },
      {
        "station": "সিলেট",
        "arrival": "05:00",
        "departure": "",
        "halt": "",
        "duration": "01:15"
      }
    ],
    "totalDuration": "07:00"
  },
  "৭৪০": {
    "name": "উপবন এক্সপ্রেস",
    "runsOn": [
      "শুক্র",
      "শনি",
      "রবি",
      "মঙ্গল",
      "বুধ",
      "বৃহস্পতি"
    ],
    "routes": [
      {
        "station": "সিলেট",
        "arrival": "",
        "departure": "23:30",
        "halt": "",
        "duration": ""
      },
      {
        "station": "মাইজগাঁও",
        "arrival": "00:09",
        "departure": "00:11",
        "halt": "00:02",
        "duration": "00:39"
      },
      {
        "station": "বরমচাল",
        "arrival": "00:28",
        "departure": "00:30",
        "halt": "00:02",
        "duration": "00:17"
      },
      {
        "station": "কুলাউড়া",
        "arrival": "00:43",
        "departure": "00:46",
        "halt": "00:03",
        "duration": "00:13"
      },
      {
        "station": "শমসেরনগর",
        "arrival": "01:09",
        "departure": "01:11",
        "halt": "00:02",
        "duration": "00:23"
      },
      {
        "station": "ভানুগাছ",
        "arrival": "01:20",
        "departure": "01:22",
        "halt": "00:02",
        "duration": "00:09"
      },
      {
        "station": "শ্রীমঙ্গল",
        "arrival": "01:41",
        "departure": "01:44",
        "halt": "00:03",
        "duration": "00:19"
      },
      {
        "station": "শায়েস্তাগঞ্জ",
        "arrival": "02:30",
        "departure": "02:33",
        "halt": "00:03",
        "duration": "00:46"
      },
      {
        "station": "ভৈরব",
        "arrival": "04:03",
        "departure": "04:06",
        "halt": "00:03",
        "duration": "01:30"
      },
      {
        "station": "নরসিংদী",
        "arrival": "04:34",
        "departure": "04:36",
        "halt": "00:02",
        "duration": "00:28"
      },
      {
        "station": "বিমানবন্দর",
        "arrival": "05:12",
        "departure": "05:15",
        "halt": "00:03",
        "duration": "00:36"
      },
      {
        "station": "ঢাকা",
        "arrival": "05:40",
        "departure": "",
        "halt": "",
        "duration": "00:25"
      }
    ],
    "totalDuration": "06:10"
  },
  "৭১৭": {
    "name": "জয়ন্তিকা এক্সপ্রেস",
    "runsOn": [
      "শুক্র",
      "শনি",
      "রবি",
      "সোম",
      "বুধ",
      "বৃহস্পতি"
    ],
    "routes": [
      {
        "station": "ঢাকা",
        "arrival": "",
        "departure": "11:15",
        "halt": "",
        "duration": ""
      },
      {
        "station": "বিমানবন্দর",
        "arrival": "11:38",
        "departure": "11:43",
        "halt": "00:05",
        "duration": "00:23"
      },
      {
        "station": "আশুগঞ্জ",
        "arrival": "12:55",
        "departure": "12:57",
        "halt": "00:02",
        "duration": "01:12"
      },
      {
        "station": "বি বাড়িয়া",
        "arrival": "13:11",
        "departure": "13:15",
        "halt": "00:04",
        "duration": "00:14"
      },
      {
        "station": "আজমপুর",
        "arrival": "13:37",
        "departure": "13:39",
        "halt": "00:02",
        "duration": "00:22"
      },
      {
        "station": "মুকুন্দপুর",
        "arrival": "13:52",
        "departure": "13:54",
        "halt": "00:02",
        "duration": "00:13"
      },
      {
        "station": "হরষপুর",
        "arrival": "14:04",
        "departure": "14:06",
        "halt": "00:02",
        "duration": "00:10"
      },
      {
        "station": "মনতলা",
        "arrival": "14:30",
        "departure": "14:33",
        "halt": "00:03",
        "duration": "00:24"
      },
      {
        "station": "নয়াপাড়া",
        "arrival": "14:47",
        "departure": "14:49",
        "halt": "00:02",
        "duration": "00:14"
      },
      {
        "station": "শাহজীবাজার",
        "arrival": "15:00",
        "departure": "15:02",
        "halt": "00:02",
        "duration": "00:11"
      },
      {
        "station": "শায়েস্তাগঞ্জ",
        "arrival": "15:21",
        "departure": "15:24",
        "halt": "00:03",
        "duration": "00:19"
      },
      {
        "station": "শ্রীমঙ্গল",
        "arrival": "16:01",
        "departure": "16:04",
        "halt": "00:03",
        "duration": "00:37"
      },
      {
        "station": "ভানুগাছ",
        "arrival": "16:23",
        "departure": "16:25",
        "halt": "00:02",
        "duration": "00:19"
      },
      {
        "station": "কুলাউড়া",
        "arrival": "17:05",
        "departure": "17:09",
        "halt": "00:04",
        "duration": "00:40"
      },
      {
        "station": "মাইজগাঁও",
        "arrival": "17:33",
        "departure": "17:35",
        "halt": "00:02",
        "duration": "00:24"
      },
      {
        "station": "সিলেট",
        "arrival": "19:00",
        "departure": "",
        "halt": "",
        "duration": "01:25"
      }
    ],
    "totalDuration": "07:45"
  },
  "৭১৮": {
    "name": "জয়ন্তিকা এক্সপ্রেস",
    "runsOn": [
      "শুক্র",
      "শনি",
      "রবি",
      "সোম",
      "মঙ্গল",
      "বুধ"
    ],
    "routes": [
      {
        "station": "সিলেট",
        "arrival": "",
        "departure": "12:00",
        "halt": "",
        "duration": ""
      },
      {
        "station": "মাইজগাঁও",
        "arrival": "12:48",
        "departure": "12:50",
        "halt": "00:02",
        "duration": "00:48"
      },
      {
        "station": "কুলাউড়া",
        "arrival": "13:17",
        "departure": "13:20",
        "halt": "00:03",
        "duration": "00:27"
      },
      {
        "station": "ভানুগাছ",
        "arrival": "14:19",
        "departure": "14:21",
        "halt": "00:02",
        "duration": "00:59"
      },
      {
        "station": "শ্রীমঙ্গল",
        "arrival": "14:40",
        "departure": "14:45",
        "halt": "00:05",
        "duration": "00:19"
      },
      {
        "station": "শায়েস্তাগঞ্জ",
        "arrival": "15:22",
        "departure": "15:25",
        "halt": "00:03",
        "duration": "00:37"
      },
      {
        "station": "শাহজীবাজার",
        "arrival": "15:37",
        "departure": "15:39",
        "halt": "00:02",
        "duration": "00:12"
      },
      {
        "station": "নয়াপাড়া",
        "arrival": "15:50",
        "departure": "15:52",
        "halt": "00:02",
        "duration": "00:11"
      },
      {
        "station": "মনতলা",
        "arrival": "16:07",
        "departure": "16:09",
        "halt": "00:02",
        "duration": "00:15"
      },
      {
        "station": "হরষপুর",
        "arrival": "16:18",
        "departure": "16:20",
        "halt": "00:02",
        "duration": "00:09"
      },
      {
        "station": "মুকুন্দপুর",
        "arrival": "16:30",
        "departure": "16:32",
        "halt": "00:02",
        "duration": "00:10"
      },
      {
        "station": "আজমপুর",
        "arrival": "16:46",
        "departure": "16:48",
        "halt": "00:02",
        "duration": "00:14"
      },
      {
        "station": "বি বাড়িয়া",
        "arrival": "17:09",
        "departure": "17:13",
        "halt": "00:04",
        "duration": "00:21"
      },
      {
        "station": "আশুগঞ্জ",
        "arrival": "17:28",
        "departure": "17:30",
        "halt": "00:02",
        "duration": "00:15"
      },
      {
        "station": "বিমানবন্দর",
        "arrival": "18:40",
        "departure": "",
        "halt": "",
        "duration": "01:10"
      },
      {
        "station": "ঢাকা",
        "arrival": "19:15",
        "departure": "",
        "halt": "",
        "duration": ""
      }
    ],
    "totalDuration": "07:15"
  },
  "৭০৯": {
    "name": "পারাবত এক্সপ্রেস",
    "runsOn": [
      "শুক্র",
      "শনি",
      "রবি",
      "মঙ্গল",
      "বুধ",
      "বৃহস্পতি"
    ],
    "routes": [
      {
        "station": "ঢাকা",
        "arrival": "",
        "departure": "06:30",
        "halt": "",
        "duration": ""
      },
      {
        "station": "বিমানবন্দর",
        "arrival": "06:53",
        "departure": "06:58",
        "halt": "00:05",
        "duration": "00:23"
      },
      {
        "station": "ভৈরব",
        "arrival": "08:03",
        "departure": "08:06",
        "halt": "00:03",
        "duration": "01:05"
      },
      {
        "station": "বি বাড়িয়া",
        "arrival": "08:26",
        "departure": "08:29",
        "halt": "00:03",
        "duration": "00:20"
      },
      {
        "station": "আজমপুর",
        "arrival": "08:50",
        "departure": "08:52",
        "halt": "00:02",
        "duration": "00:21"
      },
      {
        "station": "নয়াপাড়া",
        "arrival": "09:30",
        "departure": "09:32",
        "halt": "00:02",
        "duration": "00:38"
      },
      {
        "station": "শায়েস্তাগঞ্জ",
        "arrival": "09:52",
        "departure": "09:55",
        "halt": "00:03",
        "duration": "00:20"
      },
      {
        "station": "শ্রীমঙ্গল",
        "arrival": "10:32",
        "departure": "10:35",
        "halt": "00:03",
        "duration": "00:37"
      },
      {
        "station": "ভানুগাছ",
        "arrival": "10:54",
        "departure": "10:56",
        "halt": "00:02",
        "duration": "00:19"
      },
      {
        "station": "কুলাউড়া",
        "arrival": "11:25",
        "departure": "11:28",
        "halt": "00:03",
        "duration": "00:29"
      },
      {
        "station": "মাইজগাঁও",
        "arrival": "11:55",
        "departure": "11:57",
        "halt": "00:02",
        "duration": "00:27"
      },
      {
        "station": "সিলেট",
        "arrival": "13:00",
        "departure": "",
        "halt": "",
        "duration": "01:03"
      }
    ],
    "totalDuration": "06:30"
  },
  "৭১০": {
    "name": "পারাবত এক্সপ্রেস",
    "runsOn": [
      "শুক্র",
      "শনি",
      "রবি",
      "মঙ্গল",
      "বুধ",
      "বৃহস্পতি"
    ],
    "routes": [
      {
        "station": "সিলেট",
        "arrival": "",
        "departure": "16:00",
        "halt": "",
        "duration": ""
      },
      {
        "station": "মাইজগাঁও",
        "arrival": "16:39",
        "departure": "16:41",
        "halt": "00:02",
        "duration": "00:39"
      },
      {
        "station": "কুলাউড়া",
        "arrival": "17:06",
        "departure": "17:09",
        "halt": "00:03",
        "duration": "00:25"
      },
      {
        "station": "ভানুগাছ",
        "arrival": "17:39",
        "departure": "17:41",
        "halt": "00:02",
        "duration": "00:30"
      },
      {
        "station": "শ্রীমঙ্গল",
        "arrival": "17:59",
        "departure": "18:02",
        "halt": "00:03",
        "duration": "00:18"
      },
      {
        "station": "শায়েস্তাগঞ্জ",
        "arrival": "18:46",
        "departure": "18:49",
        "halt": "00:03",
        "duration": "00:44"
      },
      {
        "station": "নয়াপাড়া",
        "arrival": "19:10",
        "departure": "19:12",
        "halt": "00:02",
        "duration": "00:21"
      },
      {
        "station": "আজমপুর",
        "arrival": "20:05",
        "departure": "20:07",
        "halt": "00:02",
        "duration": "00:53"
      },
      {
        "station": "বি বাড়িয়া",
        "arrival": "20:30",
        "departure": "20:34",
        "halt": "00:04",
        "duration": "00:23"
      },
      {
        "station": "ভৈরব",
        "arrival": "20:55",
        "departure": "20:58",
        "halt": "00:03",
        "duration": "00:21"
      },
      {
        "station": "বিমানবন্দর",
        "arrival": "22:12",
        "departure": "",
        "halt": "",
        "duration": "01:14"
      },
      {
        "station": "ঢাকা",
        "arrival": "22:40",
        "departure": "",
        "halt": "",
        "duration": ""
      }
    ],
    "totalDuration": "06:40"
  },
  "৭৪১": {
    "name": "তূর্ণা",
    "runsOn": [
      "শুক্র",
      "শনি",
      "রবি",
      "সোম",
      "মঙ্গল",
      "বুধ",
      "বৃহস্পতি"
    ],
    "routes": [
      {
        "station": "চট্টগ্রাম",
        "arrival": "",
        "departure": "23:30",
        "halt": "",
        "duration": ""
      },
      {
        "station": "ফেনী",
        "arrival": "00:50",
        "departure": "00:52",
        "halt": "00:02",
        "duration": "01:20"
      },
      {
        "station": "লাকসাম",
        "arrival": "01:30",
        "departure": "01:32",
        "halt": "00:02",
        "duration": "00:38"
      },
      {
        "station": "কুমিল্লা",
        "arrival": "01:55",
        "departure": "01:57",
        "halt": "00:02",
        "duration": "00:23"
      },
      {
        "station": "আখাউড়া",
        "arrival": "02:47",
        "departure": "02:50",
        "halt": "00:03",
        "duration": "00:50"
      },
      {
        "station": "বি বাড়িয়া",
        "arrival": "03:07",
        "departure": "03:10",
        "halt": "00:03",
        "duration": "00:17"
      },
      {
        "station": "ভৈরব",
        "arrival": "03:30",
        "departure": "03:33",
        "halt": "00:03",
        "duration": "00:20"
      },
      {
        "station": "বিমানবন্দর",
        "arrival": "04:35",
        "departure": "04:38",
        "halt": "00:03",
        "duration": "01:02"
      },
      {
        "station": "ঢাকা",
        "arrival": "05:10",
        "departure": "",
        "halt": "",
        "duration": "00:32"
      }
    ],
    "totalDuration": "05:40"
  },
  "৭৪২": {
    "name": "তূর্ণা",
    "runsOn": [
      "শুক্র",
      "শনি",
      "রবি",
      "সোম",
      "মঙ্গল",
      "বুধ",
      "বৃহস্পতি"
    ],
    "routes": [
      {
        "station": "ঢাকা",
        "arrival": "",
        "departure": "23:15",
        "halt": "",
        "duration": ""
      },
      {
        "station": "বিমানবন্দর",
        "arrival": "23:38",
        "departure": "23:43",
        "halt": "00:05",
        "duration": "00:23"
      },
      {
        "station": "ভৈরব",
        "arrival": "00:49",
        "departure": "00:52",
        "halt": "00:03",
        "duration": "01:06"
      },
      {
        "station": "বি বাড়িয়া",
        "arrival": "01:12",
        "departure": "01:16",
        "halt": "00:04",
        "duration": "00:20"
      },
      {
        "station": "আখাউড়া",
        "arrival": "01:47",
        "departure": "01:50",
        "halt": "00:03",
        "duration": "00:31"
      },
      {
        "station": "কুমিল্লা",
        "arrival": "02:33",
        "departure": "02:35",
        "halt": "00:02",
        "duration": "00:43"
      },
      {
        "station": "লাকসাম",
        "arrival": "02:58",
        "departure": "03:00",
        "halt": "00:02",
        "duration": "00:23"
      },
      {
        "station": "ফেনী",
        "arrival": "03:40",
        "departure": "03:42",
        "halt": "00:02",
        "duration": "00:40"
      },
      {
        "station": "চট্টগ্রাম",
        "arrival": "05:15",
        "departure": "",
        "halt": "",
        "duration": "01:33"
      }
    ],
    "totalDuration": "06:00"
  },
  "১১": {
    "name": "ঢাকা এক্সপ্রেস",
    "runsOn": [
      "শুক্র",
      "শনি",
      "রবি",
      "সোম",
      "মঙ্গল",
      "বুধ",
      "বৃহস্পতি"
    ],
    "routes": [
      {
        "station": "নোয়াখালী",
        "arrival": "",
        "departure": "20:45",
        "halt": "",
        "duration": ""
      },
      {
        "station": "হরিনারায়ণপুর",
        "arrival": "",
        "departure": "20:50",
        "halt": "",
        "duration": ""
      },
      {
        "station": "মাইজদী কোর্ট",
        "arrival": "",
        "departure": "20:55",
        "halt": "",
        "duration": ""
      },
      {
        "station": "মাইজদী",
        "arrival": "",
        "departure": "21:05",
        "halt": "",
        "duration": ""
      },
      {
        "station": "চৌমুহনী",
        "arrival": "",
        "departure": "21:18",
        "halt": "",
        "duration": ""
      },
      {
        "station": "বজরা",
        "arrival": "",
        "departure": "21:33",
        "halt": "",
        "duration": ""
      },
      {
        "station": "সোনাইমুড়ি",
        "arrival": "",
        "departure": "21:43",
        "halt": "",
        "duration": ""
      },
      {
        "station": "বিপুলাসার",
        "arrival": "",
        "departure": "21:56",
        "halt": "",
        "duration": ""
      },
      {
        "station": "নাথেরপেটুয়া",
        "arrival": "",
        "departure": "22:06",
        "halt": "",
        "duration": ""
      },
      {
        "station": "খিলা",
        "arrival": "",
        "departure": "22:16",
        "halt": "",
        "duration": ""
      },
      {
        "station": "দৌলতগঞ্জ",
        "arrival": "",
        "departure": "22:30",
        "halt": "",
        "duration": ""
      },
      {
        "station": "লাকসাম",
        "arrival": "",
        "departure": "22:45",
        "halt": "",
        "duration": ""
      },
      {
        "station": "কুমিল্লা",
        "arrival": "",
        "departure": "23:19",
        "halt": "",
        "duration": ""
      },
      {
        "station": "আখাউড়া",
        "arrival": "",
        "departure": "00:25",
        "halt": "",
        "duration": ""
      },
      {
        "station": "বি বাড়িয়া",
        "arrival": "",
        "departure": "00:50",
        "halt": "",
        "duration": ""
      },
      {
        "station": "আশুগঞ্জ",
        "arrival": "",
        "departure": "01:11",
        "halt": "",
        "duration": ""
      },
      {
        "station": "ভৈরব",
        "arrival": "",
        "departure": "01:22",
        "halt": "",
        "duration": ""
      },
      {
        "station": "দৌলতকান্দি",
        "arrival": "",
        "departure": "01:38",
        "halt": "",
        "duration": ""
      },
      {
        "station": "আমিরগঞ্জ",
        "arrival": "",
        "departure": "02:03",
        "halt": "",
        "duration": ""
      },
      {
        "station": "নরসিংদী",
        "arrival": "",
        "departure": "02:13",
        "halt": "",
        "duration": ""
      },
      {
        "station": "জিনারদী",
        "arrival": "",
        "departure": "02:25",
        "halt": "",
        "duration": ""
      },
      {
        "station": "ঘোড়াশাল ফ্ল্যাগ",
        "arrival": "",
        "departure": "02:37",
        "halt": "",
        "duration": ""
      },
      {
        "station": "টঙ্গী",
        "arrival": "",
        "departure": "03:08",
        "halt": "",
        "duration": ""
      },
      {
        "station": "বিমানবন্দর",
        "arrival": "",
        "departure": "03:38",
        "halt": "",
        "duration": ""
      },
      {
        "station": "ক্যান্টনমেন্ট",
        "arrival": "",
        "departure": "03:50",
        "halt": "",
        "duration": ""
      },
      {
        "station": "তেজগাঁও",
        "arrival": "",
        "departure": "04:00",
        "halt": "",
        "duration": ""
      },
      {
        "station": "ঢাকা",
        "arrival": "",
        "departure": "06:15",
        "halt": "",
        "duration": ""
      }
    ],
    "totalDuration": ""
  },
  "১২": {
    "name": "নোয়াখালী এক্সপ্রেস",
    "runsOn": [
      "শুক্র",
      "শনি",
      "রবি",
      "সোম",
      "মঙ্গল",
      "বুধ",
      "বৃহস্পতি"
    ],
    "routes": [
      {
        "station": "ঢাকা",
        "arrival": "",
        "departure": "19:10",
        "halt": "",
        "duration": ""
      },
      {
        "station": "তেজগাঁও",
        "arrival": "",
        "departure": "19:21",
        "halt": "",
        "duration": ""
      },
      {
        "station": "ক্যান্টনমেন্ট",
        "arrival": "",
        "departure": "19:32",
        "halt": "",
        "duration": ""
      },
      {
        "station": "বিমানবন্দর",
        "arrival": "",
        "departure": "19:42",
        "halt": "",
        "duration": ""
      },
      {
        "station": "টঙ্গী",
        "arrival": "",
        "departure": "19:55",
        "halt": "",
        "duration": ""
      },
      {
        "station": "আড়িখোলা",
        "arrival": "",
        "departure": "20:18",
        "halt": "",
        "duration": ""
      },
      {
        "station": "ঘোড়াশাল ফ্ল্যাগ",
        "arrival": "",
        "departure": "20:30",
        "halt": "",
        "duration": ""
      },
      {
        "station": "জিনারদী",
        "arrival": "",
        "departure": "20:42",
        "halt": "",
        "duration": ""
      },
      {
        "station": "নরসিংদী",
        "arrival": "",
        "departure": "20:52",
        "halt": "",
        "duration": ""
      },
      {
        "station": "আমিরগঞ্জ",
        "arrival": "",
        "departure": "21:03",
        "halt": "",
        "duration": ""
      },
      {
        "station": "খানাবাড়ি",
        "arrival": "",
        "departure": "21:13",
        "halt": "",
        "duration": ""
      },
      {
        "station": "মেথিকান্দা",
        "arrival": "",
        "departure": "21:28",
        "halt": "",
        "duration": ""
      },
      {
        "station": "দৌলতকান্দি",
        "arrival": "",
        "departure": "21:43",
        "halt": "",
        "duration": ""
      },
      {
        "station": "ভৈরব",
        "arrival": "",
        "departure": "21:52",
        "halt": "",
        "duration": ""
      },
      {
        "station": "আশুগঞ্জ",
        "arrival": "",
        "departure": "22:10",
        "halt": "",
        "duration": ""
      },
      {
        "station": "তালশহর",
        "arrival": "",
        "departure": "22:20",
        "halt": "",
        "duration": ""
      },
      {
        "station": "বি বাড়িয়া",
        "arrival": "",
        "departure": "22:35",
        "halt": "",
        "duration": ""
      },
      {
        "station": "আখাউড়া",
        "arrival": "",
        "departure": "23:15",
        "halt": "",
        "duration": ""
      },
      {
        "station": "কুমিল্লা",
        "arrival": "",
        "departure": "00:08",
        "halt": "",
        "duration": ""
      },
      {
        "station": "লাকসাম",
        "arrival": "",
        "departure": "00:40",
        "halt": "",
        "duration": ""
      },
      {
        "station": "খিলা",
        "arrival": "",
        "departure": "01:05",
        "halt": "",
        "duration": ""
      },
      {
        "station": "নাথেরপেটুয়া",
        "arrival": "",
        "departure": "01:17",
        "halt": "",
        "duration": ""
      },
      {
        "station": "বিপুলাসার",
        "arrival": "",
        "departure": "01:28",
        "halt": "",
        "duration": ""
      },
      {
        "station": "সোনাইমুড়ি",
        "arrival": "",
        "departure": "01:37",
        "halt": "",
        "duration": ""
      },
      {
        "station": "বজরা",
        "arrival": "",
        "departure": "01:51",
        "halt": "",
        "duration": ""
      },
      {
        "station": "চৌমুহনী",
        "arrival": "",
        "departure": "02:02",
        "halt": "",
        "duration": ""
      },
      {
        "station": "মাইজদী",
        "arrival": "",
        "departure": "02:18",
        "halt": "",
        "duration": ""
      },
      {
        "station": "মাইজদী কোর্ট",
        "arrival": "",
        "departure": "02:26",
        "halt": "",
        "duration": ""
      },
      {
        "station": "হরিনারায়ণপুর",
        "arrival": "",
        "departure": "02:35",
        "halt": "",
        "duration": ""
      },
      {
        "station": "নোয়াখালী",
        "arrival": "",
        "departure": "02:55",
        "halt": "",
        "duration": ""
      }
    ],
    "totalDuration": ""
  },
  "২": {
    "name": "চট্টগ্রাম মেইল",
    "runsOn": [
      "শুক্র",
      "শনি",
      "রবি",
      "সোম",
      "মঙ্গল",
      "বুধ",
      "বৃহস্পতি"
    ],
    "routes": [
      {
        "station": "ঢাকা",
        "arrival": "",
        "departure": "23:45",
        "halt": "",
        "duration": ""
      },
      {
        "station": "ক্যান্টনমেন্ট",
        "arrival": "",
        "departure": "00:02",
        "halt": "",
        "duration": ""
      },
      {
        "station": "বিমানবন্দর",
        "arrival": "",
        "departure": "00:12",
        "halt": "",
        "duration": ""
      },
      {
        "station": "টঙ্গী",
        "arrival": "",
        "departure": "00:26",
        "halt": "",
        "duration": ""
      },
      {
        "station": "নরসিংদী",
        "arrival": "",
        "departure": "01:00",
        "halt": "",
        "duration": ""
      },
      {
        "station": "মেথিকান্দা",
        "arrival": "",
        "departure": "01:23",
        "halt": "",
        "duration": ""
      },
      {
        "station": "ভৈরব",
        "arrival": "",
        "departure": "01:40",
        "halt": "",
        "duration": ""
      },
      {
        "station": "আশুগঞ্জ",
        "arrival": "",
        "departure": "01:58",
        "halt": "",
        "duration": ""
      },
      {
        "station": "বি বাড়িয়া",
        "arrival": "",
        "departure": "02:15",
        "halt": "",
        "duration": ""
      },
      {
        "station": "আখাউড়া",
        "arrival": "",
        "departure": "02:50",
        "halt": "",
        "duration": ""
      },
      {
        "station": "কুমিল্লা",
        "arrival": "",
        "departure": "03:43",
        "halt": "",
        "duration": ""
      },
      {
        "station": "লাকসাম",
        "arrival": "",
        "departure": "04:11",
        "halt": "",
        "duration": ""
      },
      {
        "station": "হাসানপুর",
        "arrival": "",
        "departure": "04:35",
        "halt": "",
        "duration": ""
      },
      {
        "station": "ফেনী",
        "arrival": "",
        "departure": "05:00",
        "halt": "",
        "duration": ""
      },
      {
        "station": "সীতাকুণ্ড",
        "arrival": "",
        "departure": "05:57",
        "halt": "",
        "duration": ""
      },
      {
        "station": "ভাটিয়ারী",
        "arrival": "",
        "departure": "06:25",
        "halt": "",
        "duration": ""
      },
      {
        "station": "পাহাড়তলী",
        "arrival": "",
        "departure": "06:40",
        "halt": "",
        "duration": ""
      },
      {
        "station": "চট্টগ্রাম",
        "arrival": "",
        "departure": "07:10",
        "halt": "",
        "duration": ""
      }
    ],
    "totalDuration": ""
  },
  "১": {
    "name": "ঢাকা মেইল",
    "runsOn": [
      "শুক্র",
      "শনি",
      "রবি",
      "সোম",
      "মঙ্গল",
      "বুধ",
      "বৃহস্পতি"
    ],
    "routes": [
      {
        "station": "চট্টগ্রাম",
        "arrival": "",
        "departure": "23:45",
        "halt": "",
        "duration": ""
      },
      {
        "station": "ভাটিয়ারী",
        "arrival": "",
        "departure": "00:03",
        "halt": "",
        "duration": ""
      },
      {
        "station": "ফেনী",
        "arrival": "",
        "departure": "01:17",
        "halt": "",
        "duration": ""
      },
      {
        "station": "লাকসাম",
        "arrival": "",
        "departure": "02:03",
        "halt": "",
        "duration": ""
      },
      {
        "station": "কুমিল্লা",
        "arrival": "",
        "departure": "02:31",
        "halt": "",
        "duration": ""
      },
      {
        "station": "আখাউড়া",
        "arrival": "",
        "departure": "03:35",
        "halt": "",
        "duration": ""
      },
      {
        "station": "বি বাড়িয়া",
        "arrival": "",
        "departure": "03:57",
        "halt": "",
        "duration": ""
      },
      {
        "station": "আশুগঞ্জ",
        "arrival": "",
        "departure": "04:16",
        "halt": "",
        "duration": ""
      },
      {
        "station": "ভৈরব",
        "arrival": "",
        "departure": "04:26",
        "halt": "",
        "duration": ""
      },
      {
        "station": "মেথিকান্দা",
        "arrival": "",
        "departure": "04:45",
        "halt": "",
        "duration": ""
      },
      {
        "station": "নরসিংদী",
        "arrival": "",
        "departure": "05:04",
        "halt": "",
        "duration": ""
      },
      {
        "station": "ঘোড়াশাল ফ্ল্যাগ",
        "arrival": "",
        "departure": "05:23",
        "halt": "",
        "duration": ""
      },
      {
        "station": "আড়িখোলা",
        "arrival": "",
        "departure": "05:34",
        "halt": "",
        "duration": ""
      },
      {
        "station": "টঙ্গী",
        "arrival": "",
        "departure": "05:56",
        "halt": "",
        "duration": ""
      },
      {
        "station": "বিমানবন্দর",
        "arrival": "",
        "departure": "06:12",
        "halt": "",
        "duration": ""
      },
      {
        "station": "ক্যান্টনমেন্ট",
        "arrival": "",
        "departure": "06:23",
        "halt": "",
        "duration": ""
      },
      {
        "station": "ঢাকা",
        "arrival": "",
        "departure": "07:00",
        "halt": "",
        "duration": ""
      }
    ],
    "totalDuration": ""
  },
  "৩৩": {
    "name": "তিতাস কমিউটার",
    "runsOn": [
      "শুক্র",
      "শনি",
      "রবি",
      "সোম",
      "মঙ্গল",
      "বুধ",
      "বৃহস্পতি"
    ],
    "routes": [
      {
        "station": "আখাউড়া",
        "arrival": "",
        "departure": "05:00",
        "halt": "",
        "duration": ""
      },
      {
        "station": "পাঘাচং",
        "arrival": "",
        "departure": "05:12",
        "halt": "",
        "duration": ""
      },
      {
        "station": "বি বাড়িয়া",
        "arrival": "",
        "departure": "05:23",
        "halt": "",
        "duration": ""
      },
      {
        "station": "আশুগঞ্জ",
        "arrival": "",
        "departure": "05:40",
        "halt": "",
        "duration": ""
      },
      {
        "station": "ভৈরব",
        "arrival": "",
        "departure": "05:50",
        "halt": "",
        "duration": ""
      },
      {
        "station": "দৌলতকান্দি",
        "arrival": "",
        "departure": "05:58",
        "halt": "",
        "duration": ""
      },
      {
        "station": "শ্রীনিধি",
        "arrival": "",
        "departure": "06:07",
        "halt": "",
        "duration": ""
      },
      {
        "station": "মেথিকান্দা",
        "arrival": "",
        "departure": "06:15",
        "halt": "",
        "duration": ""
      },
      {
        "station": "খানাবাড়ি",
        "arrival": "",
        "departure": "06:28",
        "halt": "",
        "duration": ""
      },
      {
        "station": "আমিরগঞ্জ",
        "arrival": "",
        "departure": "06:36",
        "halt": "",
        "duration": ""
      },
      {
        "station": "নরসিংদী",
        "arrival": "",
        "departure": "06:45",
        "halt": "",
        "duration": ""
      },
      {
        "station": "ঘোড়াশাল ফ্ল্যাগ",
        "arrival": "",
        "departure": "07:03",
        "halt": "",
        "duration": ""
      },
      {
        "station": "আড়িখোলা",
        "arrival": "",
        "departure": "07:16",
        "halt": "",
        "duration": ""
      },
      {
        "station": "পুবাইল",
        "arrival": "",
        "departure": "07:30",
        "halt": "",
        "duration": ""
      },
      {
        "station": "টঙ্গী",
        "arrival": "",
        "departure": "07:45",
        "halt": "",
        "duration": ""
      },
      {
        "station": "বিমানবন্দর",
        "arrival": "",
        "departure": "07:56",
        "halt": "",
        "duration": ""
      },
      {
        "station": "তেজগাঁও",
        "arrival": "",
        "departure": "08:20",
        "halt": "",
        "duration": ""
      },
      {
        "station": "ঢাকা",
        "arrival": "",
        "departure": "08:35",
        "halt": "",
        "duration": ""
      }
    ],
    "totalDuration": ""
  },
  "৩৬": {
    "name": "তিতাস কমিউটার",
    "runsOn": [
      "শুক্র",
      "শনি",
      "রবি",
      "সোম",
      "মঙ্গল",
      "বুধ",
      "বৃহস্পতি"
    ],
    "routes": [
      {
        "station": "ঢাকা",
        "arrival": "",
        "departure": "17:45",
        "halt": "",
        "duration": ""
      },
      {
        "station": "তেজগাঁও",
        "arrival": "",
        "departure": "17:56",
        "halt": "",
        "duration": ""
      },
      {
        "station": "বিমানবন্দর",
        "arrival": "",
        "departure": "18:13",
        "halt": "",
        "duration": ""
      },
      {
        "station": "টঙ্গী",
        "arrival": "",
        "departure": "18:25",
        "halt": "",
        "duration": ""
      },
      {
        "station": "পুবাইল",
        "arrival": "",
        "departure": "18:38",
        "halt": "",
        "duration": ""
      },
      {
        "station": "আড়িখোলা",
        "arrival": "",
        "departure": "18:50",
        "halt": "",
        "duration": ""
      },
      {
        "station": "ঘোড়াশাল ফ্ল্যাগ",
        "arrival": "",
        "departure": "19:02",
        "halt": "",
        "duration": ""
      },
      {
        "station": "নরসিংদী",
        "arrival": "",
        "departure": "19:17",
        "halt": "",
        "duration": ""
      },
      {
        "station": "আমিরগঞ্জ",
        "arrival": "",
        "departure": "19:27",
        "halt": "",
        "duration": ""
      },
      {
        "station": "খানাবাড়ি",
        "arrival": "",
        "departure": "19:36",
        "halt": "",
        "duration": ""
      },
      {
        "station": "মেথিকান্দা",
        "arrival": "",
        "departure": "19:49",
        "halt": "",
        "duration": ""
      },
      {
        "station": "শ্রীনিধি",
        "arrival": "",
        "departure": "19:59",
        "halt": "",
        "duration": ""
      },
      {
        "station": "দৌলতকান্দি",
        "arrival": "",
        "departure": "20:08",
        "halt": "",
        "duration": ""
      },
      {
        "station": "ভৈরব",
        "arrival": "",
        "departure": "20:18",
        "halt": "",
        "duration": ""
      },
      {
        "station": "আশুগঞ্জ",
        "arrival": "",
        "departure": "20:28",
        "halt": "",
        "duration": ""
      },
      {
        "station": "বি বাড়িয়া",
        "arrival": "",
        "departure": "20:46",
        "halt": "",
        "duration": ""
      },
      {
        "station": "পাঘাচং",
        "arrival": "",
        "departure": "20:58",
        "halt": "",
        "duration": ""
      },
      {
        "station": "আখাউড়া",
        "arrival": "",
        "departure": "21:30",
        "halt": "",
        "duration": ""
      }
    ],
    "totalDuration": ""
  },
  "৩৪": {
    "name": "তিতাস কমিউটার",
    "runsOn": [
      "শুক্র",
      "শনি",
      "রবি",
      "সোম",
      "মঙ্গল",
      "বুধ",
      "বৃহস্পতি"
    ],
    "routes": [
      {
        "station": "ঢাকা",
        "arrival": "",
        "departure": "09:45",
        "halt": "",
        "duration": ""
      },
      {
        "station": "বিমানবন্দর",
        "arrival": "",
        "departure": "10:10",
        "halt": "",
        "duration": ""
      },
      {
        "station": "টঙ্গী",
        "arrival": "",
        "departure": "10:22",
        "halt": "",
        "duration": ""
      },
      {
        "station": "নরসিংদী",
        "arrival": "",
        "departure": "11:01",
        "halt": "",
        "duration": ""
      },
      {
        "station": "আমিরগঞ্জ",
        "arrival": "",
        "departure": "11:11",
        "halt": "",
        "duration": ""
      },
      {
        "station": "মেথিকান্দা",
        "arrival": "",
        "departure": "11:28",
        "halt": "",
        "duration": ""
      },
      {
        "station": "ভৈরব",
        "arrival": "",
        "departure": "11:56",
        "halt": "",
        "duration": ""
      },
      {
        "station": "আশুগঞ্জ",
        "arrival": "",
        "departure": "12:08",
        "halt": "",
        "duration": ""
      },
      {
        "station": "বি বাড়িয়া",
        "arrival": "",
        "departure": "12:30",
        "halt": "",
        "duration": ""
      }
    ],
    "totalDuration": ""
  },
  "৩৫": {
    "name": "তিতাস কমিউটার",
    "runsOn": [
      "শুক্র",
      "শনি",
      "রবি",
      "সোম",
      "মঙ্গল",
      "বুধ",
      "বৃহস্পতি"
    ],
    "routes": [
      {
        "station": "বি বাড়িয়া",
        "arrival": "",
        "departure": "13:10",
        "halt": "",
        "duration": ""
      },
      {
        "station": "আশুগঞ্জ",
        "arrival": "",
        "departure": "13:25",
        "halt": "",
        "duration": ""
      },
      {
        "station": "ভৈরব",
        "arrival": "",
        "departure": "13:34",
        "halt": "",
        "duration": ""
      },
      {
        "station": "মেথিকান্দা",
        "arrival": "",
        "departure": "13:51",
        "halt": "",
        "duration": ""
      },
      {
        "station": "আমিরগঞ্জ",
        "arrival": "",
        "departure": "14:06",
        "halt": "",
        "duration": ""
      },
      {
        "station": "নরসিংদী",
        "arrival": "",
        "departure": "14:15",
        "halt": "",
        "duration": ""
      },
      {
        "station": "টঙ্গী",
        "arrival": "",
        "departure": "14:50",
        "halt": "",
        "duration": ""
      },
      {
        "station": "বিমানবন্দর",
        "arrival": "",
        "departure": "15:00",
        "halt": "",
        "duration": ""
      },
      {
        "station": "ঢাকা",
        "arrival": "",
        "departure": "15:30",
        "halt": "",
        "duration": ""
      }
    ],
    "totalDuration": ""
  },
  "২১০১": {
    "name": "নরসিংদী কমিউটার",
    "runsOn": [
      "শুক্র",
      "শনি",
      "রবি",
      "সোম",
      "মঙ্গল",
      "বুধ",
      "বৃহস্পতি"
    ],
    "routes": [
      {
        "station": "ভৈরব",
        "arrival": "",
        "departure": "06:45",
        "halt": "",
        "duration": ""
      },
      {
        "station": "দৌলতকান্দি",
        "arrival": "",
        "departure": "06:53",
        "halt": "",
        "duration": ""
      },
      {
        "station": "মেথিকান্দা",
        "arrival": "",
        "departure": "07:08",
        "halt": "",
        "duration": ""
      },
      {
        "station": "নরসিংদী",
        "arrival": "",
        "departure": "07:33",
        "halt": "",
        "duration": ""
      },
      {
        "station": "ঘোড়াশাল ফ্ল্যাগ",
        "arrival": "",
        "departure": "07:48",
        "halt": "",
        "duration": ""
      },
      {
        "station": "আড়িখোলা",
        "arrival": "",
        "departure": "07:55",
        "halt": "",
        "duration": ""
      },
      {
        "station": "টঙ্গী",
        "arrival": "",
        "departure": "08:15",
        "halt": "",
        "duration": ""
      },
      {
        "station": "বিমানবন্দর",
        "arrival": "",
        "departure": "08:25",
        "halt": "",
        "duration": ""
      },
      {
        "station": "ক্যান্টনমেন্ট",
        "arrival": "",
        "departure": "08:37",
        "halt": "",
        "duration": ""
      },
      {
        "station": "তেজগাঁও",
        "arrival": "",
        "departure": "08:50",
        "halt": "",
        "duration": ""
      },
      {
        "station": "ঢাকা",
        "arrival": "",
        "departure": "09:05",
        "halt": "",
        "duration": ""
      }
    ],
    "totalDuration": ""
  },
  "২১০৪": {
    "name": "নরসিংদী কমিউটার",
    "runsOn": [
      "শুক্র",
      "শনি",
      "রবি",
      "সোম",
      "মঙ্গল",
      "বুধ",
      "বৃহস্পতি"
    ],
    "routes": [
      {
        "station": "ঢাকা",
        "arrival": "",
        "departure": "18:30",
        "halt": "",
        "duration": ""
      },
      {
        "station": "তেজগাঁও",
        "arrival": "",
        "departure": "18:41",
        "halt": "",
        "duration": ""
      },
      {
        "station": "বিমানবন্দর",
        "arrival": "",
        "departure": "18:57",
        "halt": "",
        "duration": ""
      },
      {
        "station": "টঙ্গী",
        "arrival": "",
        "departure": "19:10",
        "halt": "",
        "duration": ""
      },
      {
        "station": "পুবাইল",
        "arrival": "",
        "departure": "19:43",
        "halt": "",
        "duration": ""
      },
      {
        "station": "আড়িখোলা",
        "arrival": "",
        "departure": "19:55",
        "halt": "",
        "duration": ""
      },
      {
        "station": "ঘোড়াশাল ফ্ল্যাগ",
        "arrival": "",
        "departure": "20:06",
        "halt": "",
        "duration": ""
      },
      {
        "station": "নরসিংদী",
        "arrival": "",
        "departure": "20:20",
        "halt": "",
        "duration": ""
      },
      {
        "station": "মেথিকান্দা",
        "arrival": "",
        "departure": "20:40",
        "halt": "",
        "duration": ""
      },
      {
        "station": "ভৈরব",
        "arrival": "",
        "departure": "21:10",
        "halt": "",
        "duration": ""
      }
    ],
    "totalDuration": ""
  },
  "৯": {
    "name": "সুরমা মেইল",
    "runsOn": [
      "শুক্র",
      "শনি",
      "রবি",
      "সোম",
      "মঙ্গল",
      "বুধ",
      "বৃহস্পতি"
    ],
    "routes": [
      {
        "station": "ঢাকা",
        "arrival": "",
        "departure": "21:00",
        "halt": "",
        "duration": ""
      },
      {
        "station": "তেজগাঁও",
        "arrival": "",
        "departure": "21:11",
        "halt": "",
        "duration": ""
      },
      {
        "station": "ক্যান্টনমেন্ট",
        "arrival": "",
        "departure": "21:23",
        "halt": "",
        "duration": ""
      },
      {
        "station": "বিমানবন্দর",
        "arrival": "",
        "departure": "21:32",
        "halt": "",
        "duration": ""
      },
      {
        "station": "টঙ্গী",
        "arrival": "",
        "departure": "21:45",
        "halt": "",
        "duration": ""
      },
      {
        "station": "ঘোড়াশাল",
        "arrival": "",
        "departure": "22:35",
        "halt": "",
        "duration": ""
      },
      {
        "station": "জিনারদী",
        "arrival": "",
        "departure": "22:45",
        "halt": "",
        "duration": ""
      },
      {
        "station": "নরসিংদী",
        "arrival": "",
        "departure": "22:55",
        "halt": "",
        "duration": ""
      },
      {
        "station": "আমিরগঞ্জ",
        "arrival": "",
        "departure": "23:08",
        "halt": "",
        "duration": ""
      },
      {
        "station": "খানাবাড়ি",
        "arrival": "",
        "departure": "23:30",
        "halt": "",
        "duration": ""
      },
      {
        "station": "হাঁটুভাঙ্গা",
        "arrival": "",
        "departure": "23:58",
        "halt": "",
        "duration": ""
      },
      {
        "station": "মেথিকান্দা",
        "arrival": "",
        "departure": "00:08",
        "halt": "",
        "duration": ""
      },
      {
        "station": "দৌলতকান্দি",
        "arrival": "",
        "departure": "00:35",
        "halt": "",
        "duration": ""
      },
      {
        "station": "ভৈরব",
        "arrival": "",
        "departure": "01:00",
        "halt": "",
        "duration": ""
      },
      {
        "station": "আশুগঞ্জ",
        "arrival": "",
        "departure": "01:19",
        "halt": "",
        "duration": ""
      },
      {
        "station": "বি বাড়িয়া",
        "arrival": "",
        "departure": "01:40",
        "halt": "",
        "duration": ""
      },
      {
        "station": "আখাউড়া",
        "arrival": "",
        "departure": "02:15",
        "halt": "",
        "duration": ""
      },
      {
        "station": "মুকুন্দপুর",
        "arrival": "",
        "departure": "02:58",
        "halt": "",
        "duration": ""
      },
      {
        "station": "হরষপুর",
        "arrival": "",
        "departure": "03:31",
        "halt": "",
        "duration": ""
      },
      {
        "station": "মাথালিয়া",
        "arrival": "",
        "departure": "03:45",
        "halt": "",
        "duration": ""
      },
      {
        "station": "নোয়াপাড়া",
        "arrival": "",
        "departure": "04:07",
        "halt": "",
        "duration": ""
      },
      {
        "station": "শাহজীবাজার",
        "arrival": "",
        "departure": "04:23",
        "halt": "",
        "duration": ""
      },
      {
        "station": "শায়েস্তাগঞ্জ",
        "arrival": "",
        "departure": "04:40",
        "halt": "",
        "duration": ""
      },
      {
        "station": "রশিদপুর",
        "arrival": "",
        "departure": "05:08",
        "halt": "",
        "duration": ""
      },
      {
        "station": "সাতগাঁও",
        "arrival": "",
        "departure": "05:28",
        "halt": "",
        "duration": ""
      },
      {
        "station": "শ্রীমঙ্গল",
        "arrival": "",
        "departure": "05:41",
        "halt": "",
        "duration": ""
      },
      {
        "station": "ভানুগাছ",
        "arrival": "",
        "departure": "06:11",
        "halt": "",
        "duration": ""
      },
      {
        "station": "শমসেরনগর",
        "arrival": "",
        "departure": "06:26",
        "halt": "",
        "duration": ""
      },
      {
        "station": "মনু",
        "arrival": "",
        "departure": "06:38",
        "halt": "",
        "duration": ""
      },
      {
        "station": "তিলকচর",
        "arrival": "",
        "departure": "06:45",
        "halt": "",
        "duration": ""
      },
      {
        "station": "লংলা",
        "arrival": "",
        "departure": "06:55",
        "halt": "",
        "duration": ""
      },
      {
        "station": "কুলাউড়া",
        "arrival": "",
        "departure": "07:10",
        "halt": "",
        "duration": ""
      },
      {
        "station": "ছকাপন",
        "arrival": "",
        "departure": "07:33",
        "halt": "",
        "duration": ""
      },
      {
        "station": "বরমচাল",
        "arrival": "",
        "departure": "07:43",
        "halt": "",
        "duration": ""
      },
      {
        "station": "ভাটেরা বাজার",
        "arrival": "",
        "departure": "07:53",
        "halt": "",
        "duration": ""
      },
      {
        "station": "মাইজগাঁও",
        "arrival": "",
        "departure": "08:10",
        "halt": "",
        "duration": ""
      },
      {
        "station": "ফেঞ্চুগঞ্জ",
        "arrival": "",
        "departure": "08:20",
        "halt": "",
        "duration": ""
      },
      {
        "station": "মোগলাবাজার",
        "arrival": "",
        "departure": "08:50",
        "halt": "",
        "duration": ""
      },
      {
        "station": "সিলেট",
        "arrival": "09:30",
        "departure": "",
        "halt": "",
        "duration": ""
      }
    ],
    "totalDuration": ""
  },
  "১০": {
    "name": "সুরমা মেইল",
    "runsOn": [
      "শুক্র",
      "শনি",
      "রবি",
      "সোম",
      "মঙ্গল",
      "বুধ",
      "বৃহস্পতি"
    ],
    "routes": [
      {
        "station": "সিলেট",
        "arrival": "",
        "departure": "20:20",
        "halt": "",
        "duration": ""
      },
      {
        "station": "মোগলাবাজার",
        "arrival": "",
        "departure": "20:40",
        "halt": "",
        "duration": ""
      },
      {
        "station": "ফেঞ্চুগঞ্জ",
        "arrival": "",
        "departure": "21:14",
        "halt": "",
        "duration": ""
      },
      {
        "station": "মাইজগাঁও",
        "arrival": "",
        "departure": "21:25",
        "halt": "",
        "duration": ""
      },
      {
        "station": "ভাটেরা বাজার",
        "arrival": "",
        "departure": "21:42",
        "halt": "",
        "duration": ""
      },
      {
        "station": "বরমচাল",
        "arrival": "",
        "departure": "21:57",
        "halt": "",
        "duration": ""
      },
      {
        "station": "ছকাপন",
        "arrival": "",
        "departure": "22:10",
        "halt": "",
        "duration": ""
      },
      {
        "station": "কুলাউড়া",
        "arrival": "",
        "departure": "22:25",
        "halt": "",
        "duration": ""
      },
      {
        "station": "লংলা",
        "arrival": "",
        "departure": "22:47",
        "halt": "",
        "duration": ""
      },
      {
        "station": "টিলাগাঁও",
        "arrival": "",
        "departure": "23:00",
        "halt": "",
        "duration": ""
      },
      {
        "station": "মনু",
        "arrival": "",
        "departure": "23:05",
        "halt": "",
        "duration": ""
      },
      {
        "station": "শমসেরনগর",
        "arrival": "",
        "departure": "23:18",
        "halt": "",
        "duration": ""
      },
      {
        "station": "ভানুগাছ",
        "arrival": "",
        "departure": "23:33",
        "halt": "",
        "duration": ""
      },
      {
        "station": "শ্রীমঙ্গল",
        "arrival": "",
        "departure": "00:30",
        "halt": "",
        "duration": ""
      },
      {
        "station": "সাতগাঁও",
        "arrival": "",
        "departure": "00:51",
        "halt": "",
        "duration": ""
      },
      {
        "station": "রশিদপুর",
        "arrival": "",
        "departure": "01:15",
        "halt": "",
        "duration": ""
      },
      {
        "station": "শায়েস্তাগঞ্জ",
        "arrival": "",
        "departure": "02:05",
        "halt": "",
        "duration": ""
      },
      {
        "station": "শাহজীবাজার",
        "arrival": "",
        "departure": "03:02",
        "halt": "",
        "duration": ""
      },
      {
        "station": "নয়াপাড়া",
        "arrival": "",
        "departure": "03:17",
        "halt": "",
        "duration": ""
      },
      {
        "station": "মনতলা",
        "arrival": "",
        "departure": "03:47",
        "halt": "",
        "duration": ""
      },
      {
        "station": "হরষপুর",
        "arrival": "",
        "departure": "04:00",
        "halt": "",
        "duration": ""
      },
      {
        "station": "মুকুন্দপুর",
        "arrival": "",
        "departure": "04:14",
        "halt": "",
        "duration": ""
      },
      {
        "station": "আখাউড়া",
        "arrival": "",
        "departure": "05:00",
        "halt": "",
        "duration": ""
      },
      {
        "station": "ভাতশালা",
        "arrival": "",
        "departure": "05:33",
        "halt": "",
        "duration": ""
      },
      {
        "station": "পাঘাচং",
        "arrival": "",
        "departure": "05:43",
        "halt": "",
        "duration": ""
      },
      {
        "station": "বি বাড়িয়া",
        "arrival": "",
        "departure": "05:55",
        "halt": "",
        "duration": ""
      },
      {
        "station": "তালশহর",
        "arrival": "",
        "departure": "06:20",
        "halt": "",
        "duration": ""
      },
      {
        "station": "আশুগঞ্জ",
        "arrival": "",
        "departure": "06:30",
        "halt": "",
        "duration": ""
      },
      {
        "station": "ভৈরব",
        "arrival": "",
        "departure": "06:38",
        "halt": "",
        "duration": ""
      },
      {
        "station": "দৌলতকান্দি",
        "arrival": "",
        "departure": "07:03",
        "halt": "",
        "duration": ""
      },
      {
        "station": "শ্রীনিধি",
        "arrival": "",
        "departure": "07:13",
        "halt": "",
        "duration": ""
      },
      {
        "station": "মেথিকান্দা",
        "arrival": "",
        "departure": "07:22",
        "halt": "",
        "duration": ""
      },
      {
        "station": "হাঁটুভাঙ্গা",
        "arrival": "",
        "departure": "07:32",
        "halt": "",
        "duration": ""
      },
      {
        "station": "খানাবাড়ি",
        "arrival": "",
        "departure": "07:42",
        "halt": "",
        "duration": ""
      },
      {
        "station": "আমিরগঞ্জ",
        "arrival": "",
        "departure": "07:52",
        "halt": "",
        "duration": ""
      },
      {
        "station": "নরসিংদী",
        "arrival": "",
        "departure": "08:02",
        "halt": "",
        "duration": ""
      },
      {
        "station": "জিনারদী",
        "arrival": "",
        "departure": "08:12",
        "halt": "",
        "duration": ""
      },
      {
        "station": "ঘোড়াশাল",
        "arrival": "",
        "departure": "08:21",
        "halt": "",
        "duration": ""
      },
      {
        "station": "ঘোড়াশাল ফ্ল্যাগ",
        "arrival": "",
        "departure": "08:28",
        "halt": "",
        "duration": ""
      },
      {
        "station": "আড়িখোলা",
        "arrival": "",
        "departure": "08:40",
        "halt": "",
        "duration": ""
      },
      {
        "station": "টঙ্গী",
        "arrival": "",
        "departure": "09:02",
        "halt": "",
        "duration": ""
      },
      {
        "station": "বিমানবন্দর",
        "arrival": "",
        "departure": "09:14",
        "halt": "",
        "duration": ""
      },
      {
        "station": "ক্যান্টনমেন্ট",
        "arrival": "",
        "departure": "09:24",
        "halt": "",
        "duration": ""
      },
      {
        "station": "তেজগাঁও",
        "arrival": "",
        "departure": "09:38",
        "halt": "",
        "duration": ""
      },
      {
        "station": "ঢাকা",
        "arrival": "09:55",
        "departure": "",
        "halt": "",
        "duration": ""
      }
    ]
  },
  "৪": {
    "name": "কর্ণফুলী কমিউটার",
    "runsOn": [
      "শুক্র",
      "শনি",
      "রবি",
      "সোম",
      "মঙ্গল",
      "বুধ",
      "বৃহস্পতি"
    ],
    "routes": [
      {
        "station": "ঢাকা",
        "arrival": "",
        "departure": "08:45",
        "halt": "",
        "duration": ""
      },
      {
        "station": "তেজগাঁও",
        "arrival": "",
        "departure": "08:56",
        "halt": "",
        "duration": ""
      },
      {
        "station": "ক্যান্টনমেন্ট",
        "arrival": "",
        "departure": "09:08",
        "halt": "",
        "duration": ""
      },
      {
        "station": "বিমানবন্দর",
        "arrival": "",
        "departure": "09:18",
        "halt": "",
        "duration": ""
      },
      {
        "station": "টঙ্গী",
        "arrival": "",
        "departure": "09:30",
        "halt": "",
        "duration": ""
      },
      {
        "station": "পুবাইল",
        "arrival": "",
        "departure": "09:43",
        "halt": "",
        "duration": ""
      },
      {
        "station": "আড়িখোলা",
        "arrival": "",
        "departure": "09:55",
        "halt": "",
        "duration": ""
      },
      {
        "station": "ঘোড়াশাল ফ্ল্যাগ",
        "arrival": "",
        "departure": "10:07",
        "halt": "",
        "duration": ""
      },
      {
        "station": "ঘোড়াশাল",
        "arrival": "",
        "departure": "10:13",
        "halt": "",
        "duration": ""
      },
      {
        "station": "জিনারদী",
        "arrival": "",
        "departure": "10:22",
        "halt": "",
        "duration": ""
      },
      {
        "station": "নরসিংদী",
        "arrival": "",
        "departure": "10:42",
        "halt": "",
        "duration": ""
      },
      {
        "station": "আমিরগঞ্জ",
        "arrival": "",
        "departure": "10:52",
        "halt": "",
        "duration": ""
      },
      {
        "station": "খানাবাড়ি",
        "arrival": "",
        "departure": "11:00",
        "halt": "",
        "duration": ""
      },
      {
        "station": "হাঁটুভাঙ্গা",
        "arrival": "",
        "departure": "11:10",
        "halt": "",
        "duration": ""
      },
      {
        "station": "মেথিকান্দা",
        "arrival": "",
        "departure": "11:18",
        "halt": "",
        "duration": ""
      },
      {
        "station": "শ্রীনিধি",
        "arrival": "",
        "departure": "11:27",
        "halt": "",
        "duration": ""
      },
      {
        "station": "দৌলতকান্দি",
        "arrival": "",
        "departure": "11:36",
        "halt": "",
        "duration": ""
      },
      {
        "station": "ভৈরব",
        "arrival": "",
        "departure": "11:45",
        "halt": "",
        "duration": ""
      },
      {
        "station": "আশুগঞ্জ",
        "arrival": "",
        "departure": "11:55",
        "halt": "",
        "duration": ""
      },
      {
        "station": "তালশহর",
        "arrival": "",
        "departure": "12:04",
        "halt": "",
        "duration": ""
      },
      {
        "station": "বি বাড়িয়া",
        "arrival": "",
        "departure": "12:18",
        "halt": "",
        "duration": ""
      },
      {
        "station": "পাঘাচং",
        "arrival": "",
        "departure": "12:30",
        "halt": "",
        "duration": ""
      },
      {
        "station": "ভাতশালা",
        "arrival": "",
        "departure": "12:39",
        "halt": "",
        "duration": ""
      },
      {
        "station": "আখাউড়া",
        "arrival": "",
        "departure": "13:00",
        "halt": "",
        "duration": ""
      },
      {
        "station": "গঙ্গাসাগর",
        "arrival": "",
        "departure": "13:12",
        "halt": "",
        "duration": ""
      },
      {
        "station": "ইমামবাড়ি",
        "arrival": "",
        "departure": "13:22",
        "halt": "",
        "duration": ""
      },
      {
        "station": "কসবা",
        "arrival": "",
        "departure": "13:31",
        "halt": "",
        "duration": ""
      },
      {
        "station": "মন্ডলবাগ",
        "arrival": "",
        "departure": "13:42",
        "halt": "",
        "duration": ""
      },
      {
        "station": "শালদানদী",
        "arrival": "",
        "departure": "13:48",
        "halt": "",
        "duration": ""
      },
      {
        "station": "শশীদল",
        "arrival": "",
        "departure": "13:54",
        "halt": "",
        "duration": ""
      },
      {
        "station": "রাজাপুর",
        "arrival": "",
        "departure": "14:03",
        "halt": "",
        "duration": ""
      },
      {
        "station": "সদর রসুলপুর",
        "arrival": "",
        "departure": "14:15",
        "halt": "",
        "duration": ""
      },
      {
        "station": "কুমিল্লা",
        "arrival": "",
        "departure": "14:26",
        "halt": "",
        "duration": ""
      },
      {
        "station": "লাকসাম",
        "arrival": "",
        "departure": "14:52",
        "halt": "",
        "duration": ""
      },
      {
        "station": "নাঙ্গলকোট",
        "arrival": "",
        "departure": "15:09",
        "halt": "",
        "duration": ""
      },
      {
        "station": "হাসানপুর",
        "arrival": "",
        "departure": "15:19",
        "halt": "",
        "duration": ""
      },
      {
        "station": "গুণবতী",
        "arrival": "",
        "departure": "15:31",
        "halt": "",
        "duration": ""
      },
      {
        "station": "ফেনী",
        "arrival": "",
        "departure": "15:48",
        "halt": "",
        "duration": ""
      },
      {
        "station": "চিনকি আস্তানা",
        "arrival": "",
        "departure": "16:12",
        "halt": "",
        "duration": ""
      },
      {
        "station": "সীতাকুণ্ড",
        "arrival": "",
        "departure": "16:47",
        "halt": "",
        "duration": ""
      },
      {
        "station": "পাহাড়তলী",
        "arrival": "",
        "departure": "17:25",
        "halt": "",
        "duration": ""
      },
      {
        "station": "চট্টগ্রাম",
        "arrival": "17:50",
        "departure": "",
        "halt": "",
        "duration": ""
      }
    ]
  },
  "৩": {
    "name": "কর্ণফুলী কমিউটার",
    "runsOn": [
      "শুক্র",
      "শনি",
      "রবি",
      "সোম",
      "মঙ্গল",
      "বুধ",
      "বৃহস্পতি"
    ],
    "routes": [
      {
        "station": "চট্টগ্রাম",
        "arrival": "",
        "departure": "09:45",
        "halt": "",
        "duration": ""
      },
      {
        "station": "পাহাড়তলী",
        "arrival": "",
        "departure": "09:55",
        "halt": "",
        "duration": ""
      },
      {
        "station": "সীতাকুণ্ড",
        "arrival": "",
        "departure": "10:30",
        "halt": "",
        "duration": ""
      },
      {
        "station": "চিনকি আস্তানা",
        "arrival": "",
        "departure": "11:05",
        "halt": "",
        "duration": ""
      },
      {
        "station": "ফেনী",
        "arrival": "",
        "departure": "11:28",
        "halt": "",
        "duration": ""
      },
      {
        "station": "গুণবতী",
        "arrival": "",
        "departure": "11:46",
        "halt": "",
        "duration": ""
      },
      {
        "station": "হাসানপুর",
        "arrival": "",
        "departure": "11:58",
        "halt": "",
        "duration": ""
      },
      {
        "station": "নাঙ্গলকোট",
        "arrival": "",
        "departure": "12:08",
        "halt": "",
        "duration": ""
      },
      {
        "station": "লাকসাম",
        "arrival": "",
        "departure": "12:25",
        "halt": "",
        "duration": ""
      },
      {
        "station": "কুমিল্লা",
        "arrival": "",
        "departure": "12:52",
        "halt": "",
        "duration": ""
      },
      {
        "station": "সদর রসুলপুর",
        "arrival": "",
        "departure": "13:04",
        "halt": "",
        "duration": ""
      },
      {
        "station": "রাজাপুর",
        "arrival": "",
        "departure": "13:16",
        "halt": "",
        "duration": ""
      },
      {
        "station": "শশীদল",
        "arrival": "",
        "departure": "13:27",
        "halt": "",
        "duration": ""
      },
      {
        "station": "শালদানদী",
        "arrival": "",
        "departure": "13:35",
        "halt": "",
        "duration": ""
      },
      {
        "station": "মন্ডলবাগ",
        "arrival": "",
        "departure": "13:41",
        "halt": "",
        "duration": ""
      },
      {
        "station": "কসবা",
        "arrival": "",
        "departure": "13:52",
        "halt": "",
        "duration": ""
      },
      {
        "station": "ইমামবাড়ি",
        "arrival": "",
        "departure": "14:01",
        "halt": "",
        "duration": ""
      },
      {
        "station": "গঙ্গাসাগর",
        "arrival": "",
        "departure": "14:11",
        "halt": "",
        "duration": ""
      },
      {
        "station": "আখাউড়া",
        "arrival": "",
        "departure": "14:25",
        "halt": "",
        "duration": ""
      },
      {
        "station": "ভাতশালা",
        "arrival": "",
        "departure": "14:38",
        "halt": "",
        "duration": ""
      },
      {
        "station": "পাঘাচং",
        "arrival": "",
        "departure": "14:47",
        "halt": "",
        "duration": ""
      },
      {
        "station": "বি বাড়িয়া",
        "arrival": "",
        "departure": "14:59",
        "halt": "",
        "duration": ""
      },
      {
        "station": "তালশহর",
        "arrival": "",
        "departure": "15:13",
        "halt": "",
        "duration": ""
      },
      {
        "station": "আশুগঞ্জ",
        "arrival": "",
        "departure": "15:23",
        "halt": "",
        "duration": ""
      },
      {
        "station": "ভৈরব",
        "arrival": "",
        "departure": "15:33",
        "halt": "",
        "duration": ""
      },
      {
        "station": "দৌলতকান্দি",
        "arrival": "",
        "departure": "15:42",
        "halt": "",
        "duration": ""
      },
      {
        "station": "শ্রীনিধি",
        "arrival": "",
        "departure": "15:51",
        "halt": "",
        "duration": ""
      },
      {
        "station": "মেথিকান্দা",
        "arrival": "",
        "departure": "16:00",
        "halt": "",
        "duration": ""
      },
      {
        "station": "হাঁটুভাঙ্গা",
        "arrival": "",
        "departure": "16:08",
        "halt": "",
        "duration": ""
      },
      {
        "station": "খানাবাড়ি",
        "arrival": "",
        "departure": "16:18",
        "halt": "",
        "duration": ""
      },
      {
        "station": "আমিরগঞ্জ",
        "arrival": "",
        "departure": "16:26",
        "halt": "",
        "duration": ""
      },
      {
        "station": "নরসিংদী",
        "arrival": "",
        "departure": "16:36",
        "halt": "",
        "duration": ""
      },
      {
        "station": "জিনারদী",
        "arrival": "",
        "departure": "16:46",
        "halt": "",
        "duration": ""
      },
      {
        "station": "ঘোড়াশাল",
        "arrival": "",
        "departure": "16:55",
        "halt": "",
        "duration": ""
      },
      {
        "station": "ঘোড়াশাল ফ্ল্যাগ",
        "arrival": "",
        "departure": "17:01",
        "halt": "",
        "duration": ""
      },
      {
        "station": "আড়িখোলা",
        "arrival": "",
        "departure": "17:13",
        "halt": "",
        "duration": ""
      },
      {
        "station": "পুবাইল",
        "arrival": "",
        "departure": "17:26",
        "halt": "",
        "duration": ""
      },
      {
        "station": "টঙ্গী",
        "arrival": "",
        "departure": "17:40",
        "halt": "",
        "duration": ""
      },
      {
        "station": "বিমানবন্দর",
        "arrival": "",
        "departure": "17:50",
        "halt": "",
        "duration": ""
      },
      {
        "station": "তেজগাঁও",
        "arrival": "",
        "departure": "18:08",
        "halt": "",
        "duration": ""
      },
      {
        "station": "ঢাকা",
        "arrival": "18:20",
        "departure": "",
        "halt": "",
        "duration": ""
      }
    ]
  }
}
